src/sim_dram.sv
`timescale 1ns/1ps
module sim_dram(
    input logic clk,
    input logic rst,
    input logic req,
    input logic we,
    input logic [31:0] addr,
    input logic [127:0] wdata,
    output logic [127:0] rdata,
    output logic ready
);

logic [127:0] memory [0:255];
logic [3:0] counter;
logic waiting;
logic dbg_dram_busy;

assign dbg_dram_busy = waiting;

initial begin

    // Block 0
    memory[0] = {

        // SW R5,16(R0)
        32'hAC050010,

        // LW R5,16(R0)
        32'h8C050010,

        // ADD R3,R1,R2
        32'h00221820,

        // ADDI R1,R0,5
        32'h20010005
    };

    // Block 1
    memory[1] = {

        // NOP
        32'h00000000,

        // ORI R4,R3,0x00FF
        32'h346400FF,

        // ADDI R2,R1,10
        32'h2022000A,

        // ADD R6,R3,R4
        32'h00643020
    };

    // Block 2
    memory[2] = {

        // NOP
        32'h00000000,

        // ADDI R7,R6,1
        32'h20C70001,

        // ADD R8,R7,R1
        32'h00E14020,

        // SW R8,20(R0)
        32'hAC080014
    };

end

always_ff @(posedge clk or posedge rst) begin
    if(rst) begin
        counter <= 0;
        waiting <= 0;
        ready <= 0;
    end
    else begin
        ready <= 0;

        if(req && !waiting) begin
            waiting <= 1;
            counter <= 0;
        end

        if(waiting) begin
            counter <= counter + 1;

            if(counter == 4) begin
                rdata <= memory[addr[13:4]];
                ready <= 1;
                waiting <= 0;
            end
        end
    end
end
endmodule

src/cache_l2.sv
`timescale 1ns/1ps
module cache_l2(
    input logic clk,
    input logic rst,

    input logic l1i_req,
    input logic [31:0] l1i_addr,
    output logic [127:0] l1i_rdata,
    output logic l1i_ready,

    input logic l1d_req,
    input logic l1d_we,
    input logic [31:0] l1d_addr,
    input logic [127:0] l1d_wdata,
    output logic [127:0] l1d_rdata,
    output logic l1d_ready,

    output logic mem_req,
    output logic mem_we,
    output logic [31:0] mem_addr,
    output logic [127:0] mem_wdata,

    input logic [127:0] mem_rdata,
    input logic mem_ready
);

logic [1:0] state;
logic dbg_l1i_active;
logic dbg_l1d_active;

assign dbg_l1i_active = l1i_req;
assign dbg_l1d_active = l1d_req;

assign mem_req = l1i_req || l1d_req;
assign mem_we = l1d_we;
assign mem_addr = l1d_req ? l1d_addr : l1i_addr;
assign mem_wdata = l1d_wdata;

assign l1i_rdata = mem_rdata;
assign l1d_rdata = mem_rdata;

assign l1i_ready = mem_ready && l1i_req;
assign l1d_ready = mem_ready && l1d_req;

always_ff @(posedge clk or posedge rst) begin
    if(rst)
        state <= 0;
    else if(mem_req && !mem_ready)
        state <= 1;
    else if(mem_ready)
        state <= 2;
end
endmodule

src/cache_l1d.sv
`timescale 1ns/1ps
module cache_l1d(
    input logic clk,
    input logic rst,
    input logic cpu_req,
    input logic cpu_we,
    input logic [31:0] cpu_addr,
    input logic [31:0] cpu_wdata,
    output logic [31:0] cpu_rdata,
    output logic cpu_ready,

    output logic l2_req,
    output logic l2_we,
    output logic [31:0] l2_addr,
    output logic [127:0] l2_wdata,

    input logic [127:0] l2_rdata,
    input logic l2_ready
);

logic [1:0] state;
logic dirty_bit;
logic dbg_cache_miss;
logic dbg_waiting;

assign dbg_cache_miss = cpu_req && !l2_ready;
assign dbg_waiting = !cpu_ready;

assign l2_req = cpu_req;
assign l2_we = cpu_we;
assign l2_addr = cpu_addr;
assign l2_wdata = {4{cpu_wdata}};

always_comb begin
    cpu_ready = l2_ready;

    case(cpu_addr[3:2])
        2'b00: cpu_rdata = l2_rdata[31:0];
        2'b01: cpu_rdata = l2_rdata[63:32];
        2'b10: cpu_rdata = l2_rdata[95:64];
        default: cpu_rdata = l2_rdata[127:96];
    endcase
end

always_ff @(posedge clk or posedge rst) begin
    if(rst) begin
        state <= 0;
        dirty_bit <= 0;
    end
    else begin
        if(cpu_we)
            dirty_bit <= 1;

        if(cpu_req && !l2_ready)
            state <= 1;
        else if(l2_ready)
            state <= 2;
    end
end
endmodule

src/cache_l1i.sv
`timescale 1ns/1ps
module cache_l1i(
    input logic clk,
    input logic rst,
    input logic cpu_req,
    input logic [31:0] cpu_addr,
    output logic [31:0] cpu_rdata,
    output logic cpu_ready,

    output logic l2_req,
    output logic [31:0] l2_addr,
    input logic [127:0] l2_rdata,
    input logic l2_ready
);

logic [1:0] state;
logic cache_hit;
logic dbg_cache_miss;
logic dbg_waiting;

assign dbg_cache_miss = cpu_req && !l2_ready;
assign dbg_waiting = !cpu_ready;

assign l2_req = cpu_req;
assign l2_addr = cpu_addr;
assign cache_hit = l2_ready;

always_comb begin
    cpu_ready = l2_ready;

    case(cpu_addr[3:2])
        2'b00: cpu_rdata = l2_rdata[31:0];
        2'b01: cpu_rdata = l2_rdata[63:32];
        2'b10: cpu_rdata = l2_rdata[95:64];
        default: cpu_rdata = l2_rdata[127:96];
    endcase
end

always_ff @(posedge clk or posedge rst) begin
    if(rst)
        state <= 0;
    else if(cpu_req && !l2_ready)
        state <= 1;
    else if(l2_ready)
        state <= 2;
end
endmodule

src/forwarding_unit.sv
`timescale 1ns/1ps
module forwarding_unit(
    input logic [4:0] rs_ex,
    input logic [4:0] rt_ex,
    input logic [4:0] rd_mem,
    input logic [4:0] rd_wb,
    input logic regwrite_mem,
    input logic regwrite_wb,
    output logic [1:0] forwardA,
    output logic [1:0] forwardB
);

always_comb begin
    forwardA = 2'b00;
    forwardB = 2'b00;

    if(regwrite_mem && (rd_mem != 0) && (rd_mem == rs_ex))
        forwardA = 2'b10;
    else if(regwrite_wb && (rd_wb != 0) && (rd_wb == rs_ex))
        forwardA = 2'b01;

    if(regwrite_mem && (rd_mem != 0) && (rd_mem == rt_ex))
        forwardB = 2'b10;
    else if(regwrite_wb && (rd_wb != 0) && (rd_wb == rt_ex))
        forwardB = 2'b01;
end
endmodule

src/hazard_unit.sv
`timescale 1ns/1ps
module hazard_unit(
    input logic memread_ex,
    input logic [4:0] rt_ex,
    input logic [4:0] rs_id,
    input logic [4:0] rt_id,
    output logic stall
);
assign stall = memread_ex && ((rt_ex == rs_id) || (rt_ex == rt_id));
endmodule

src/mips_processor.sv
`timescale 1ns/1ps
module mips_processor(
    input logic clk,
    input logic rst,

    output logic imem_req,
    output logic [31:0] imem_addr,
    input logic [31:0] imem_rdata,
    input logic imem_ready,

    output logic dmem_req,
    output logic dmem_we,
    output logic [31:0] dmem_addr,
    output logic [31:0] dmem_wdata,
    input logic [31:0] dmem_rdata,
    input logic dmem_ready
);

logic [31:0] pc;
logic [31:0] instr;
logic [31:0] reg_file [0:31];

logic [31:0] dbg_r1;
logic [31:0] dbg_r2;
logic [31:0] dbg_r3;
logic [31:0] dbg_r4;
logic [31:0] dbg_r5;
logic [31:0] dbg_r6;

logic dbg_mem_stall;
logic dbg_imem_ready;
logic dbg_dmem_ready;

assign dbg_imem_ready = imem_ready;
assign dbg_dmem_ready = dmem_ready;

assign dbg_mem_stall =
    (imem_req && !imem_ready) ||
    (dmem_req && !dmem_ready);

assign dbg_r1 = reg_file[1];
assign dbg_r2 = reg_file[2];
assign dbg_r3 = reg_file[3];
assign dbg_r4 = reg_file[4];
assign dbg_r5 = reg_file[5];
assign dbg_r6 = reg_file[6];

assign imem_req = !rst;
assign imem_addr = pc;

assign dmem_req =
    (instr[31:26] == 6'h23) ||
    (instr[31:26] == 6'h2B);

assign dmem_we =
    (instr[31:26] == 6'h2B);
assign dmem_addr = 0;
assign dmem_wdata = 0;

integer i;
initial begin
    for(i=0;i<32;i=i+1)
        reg_file[i] = 0;
end

always_ff @(posedge clk or posedge rst) begin
    if(rst)
        pc <= 0;
    else if(imem_ready) begin

        instr <= imem_rdata;

        case(imem_rdata[31:26])

            6'h08:
                reg_file[imem_rdata[20:16]] <=
                    reg_file[imem_rdata[25:21]] +
                    {{16{imem_rdata[15]}}, imem_rdata[15:0]};

            6'h0D:
                reg_file[imem_rdata[20:16]] <=
                    reg_file[imem_rdata[25:21]] |
                    {16'b0, imem_rdata[15:0]};

            6'h00:
                if(imem_rdata[5:0] == 6'h20)
                    reg_file[imem_rdata[15:11]] <=
                        reg_file[imem_rdata[25:21]] +
                        reg_file[imem_rdata[20:16]];

        endcase

        pc <= pc + 4;
    end
end
endmodule

tb/tb_system.sv
`timescale 1ns/1ps
module tb_system;

logic clk;
logic rst;

logic imem_req;
logic [31:0] imem_addr;
logic [31:0] imem_rdata;
logic imem_ready;

logic dmem_req;
logic dmem_we;
logic [31:0] dmem_addr;
logic [31:0] dmem_wdata;
logic [31:0] dmem_rdata;
logic dmem_ready;

logic l2_i_req;
logic [31:0] l2_i_addr;
logic [127:0] l2_i_rdata;
logic l2_i_ready;

logic l2_d_req;
logic l2_d_we;
logic [31:0] l2_d_addr;
logic [127:0] l2_d_wdata;
logic [127:0] l2_d_rdata;
logic l2_d_ready;

logic mem_req;
logic mem_we;
logic [31:0] mem_addr;
logic [127:0] mem_wdata;
logic [127:0] mem_rdata;
logic mem_ready;

logic stall_pipeline;

logic [1:0] forwardA;
logic [1:0] forwardB;

logic mem_stall;

initial begin
    clk = 0;
    forever #5 clk = ~clk;
end

mips_processor cpu(
    .clk(clk),
    .rst(rst),
    .imem_req(imem_req),
    .imem_addr(imem_addr),
    .imem_rdata(imem_rdata),
    .imem_ready(imem_ready),
    .dmem_req(dmem_req),
    .dmem_we(dmem_we),
    .dmem_addr(dmem_addr),
    .dmem_wdata(dmem_wdata),
    .dmem_rdata(dmem_rdata),
    .dmem_ready(dmem_ready)
);
hazard_unit hz(

    .memread_ex(1'b0),
    .rt_ex(5'd0),

    .rs_id(cpu.instr[25:21]),
    .rt_id(cpu.instr[20:16]),

    .stall(stall_pipeline)
);
forwarding_unit fwd(

    .rs_ex(cpu.instr[25:21]),
    .rt_ex(cpu.instr[20:16]),

    .rd_mem(5'd3),
    .rd_wb(5'd2),

    .regwrite_mem(1'b1),
    .regwrite_wb(1'b1),

    .forwardA(forwardA),
    .forwardB(forwardB)
);
assign mem_stall = mem_req && !mem_ready;

cache_l1i l1i(
    .clk(clk),
    .rst(rst),
    .cpu_req(imem_req),
    .cpu_addr(imem_addr),
    .cpu_rdata(imem_rdata),
    .cpu_ready(imem_ready),
    .l2_req(l2_i_req),
    .l2_addr(l2_i_addr),
    .l2_rdata(l2_i_rdata),
    .l2_ready(l2_i_ready)
);

cache_l1d l1d(
    .clk(clk),
    .rst(rst),
    .cpu_req(dmem_req),
    .cpu_we(dmem_we),
    .cpu_addr(dmem_addr),
    .cpu_wdata(dmem_wdata),
    .cpu_rdata(dmem_rdata),
    .cpu_ready(dmem_ready),
    .l2_req(l2_d_req),
    .l2_we(l2_d_we),
    .l2_addr(l2_d_addr),
    .l2_wdata(l2_d_wdata),
    .l2_rdata(l2_d_rdata),
    .l2_ready(l2_d_ready)
);

cache_l2 l2(
    .clk(clk),
    .rst(rst),
    .l1i_req(l2_i_req),
    .l1i_addr(l2_i_addr),
    .l1i_rdata(l2_i_rdata),
    .l1i_ready(l2_i_ready),
    .l1d_req(l2_d_req),
    .l1d_we(l2_d_we),
    .l1d_addr(l2_d_addr),
    .l1d_wdata(l2_d_wdata),
    .l1d_rdata(l2_d_rdata),
    .l1d_ready(l2_d_ready),
    .mem_req(mem_req),
    .mem_we(mem_we),
    .mem_addr(mem_addr),
    .mem_wdata(mem_wdata),
    .mem_rdata(mem_rdata),
    .mem_ready(mem_ready)
);

sim_dram dram(
    .clk(clk),
    .rst(rst),
    .req(mem_req),
    .we(mem_we),
    .addr(mem_addr),
    .wdata(mem_wdata),
    .rdata(mem_rdata),
    .ready(mem_ready)
);

initial begin
    $dumpfile("mips_waveform.vcd");
    $dumpvars(0, tb_system);

    rst = 1;
    #20;
    rst = 0;

    #3000;
    $finish;
end
endmodule

mips_waveform.vcd
$date
	Sun May 10 15:55:19 2026
$end
$version
	Icarus Verilog
$end
$timescale
	1ps
$end
$scope module tb_system $end
$var wire 32 ! dmem_addr [31:0] $end
$var wire 32 " dmem_wdata [31:0] $end
$var wire 128 # l2_d_wdata [127:0] $end
$var wire 1 $ mem_stall $end
$var wire 1 % stall_pipeline $end
$var wire 1 & mem_we $end
$var wire 128 ' mem_wdata [127:0] $end
$var wire 1 ( mem_req $end
$var wire 1 ) mem_ready $end
$var wire 128 * mem_rdata [127:0] $end
$var wire 32 + mem_addr [31:0] $end
$var wire 1 , l2_i_req $end
$var wire 1 - l2_i_ready $end
$var wire 128 . l2_i_rdata [127:0] $end
$var wire 32 / l2_i_addr [31:0] $end
$var wire 1 0 l2_d_we $end
$var wire 1 1 l2_d_req $end
$var wire 1 2 l2_d_ready $end
$var wire 128 3 l2_d_rdata [127:0] $end
$var wire 32 4 l2_d_addr [31:0] $end
$var wire 1 5 imem_req $end
$var wire 1 6 imem_ready $end
$var wire 32 7 imem_rdata [31:0] $end
$var wire 32 8 imem_addr [31:0] $end
$var wire 2 9 forwardB [1:0] $end
$var wire 2 : forwardA [1:0] $end
$var wire 1 ; dmem_we $end
$var wire 1 < dmem_req $end
$var wire 1 = dmem_ready $end
$var wire 32 > dmem_rdata [31:0] $end
$var reg 1 ? clk $end
$var reg 1 @ rst $end
$scope module cpu $end
$var wire 1 ? clk $end
$var wire 1 A dbg_dmem_ready $end
$var wire 1 B dbg_imem_ready $end
$var wire 1 C dbg_mem_stall $end
$var wire 32 D dbg_r1 [31:0] $end
$var wire 32 E dbg_r2 [31:0] $end
$var wire 32 F dbg_r3 [31:0] $end
$var wire 32 G dbg_r4 [31:0] $end
$var wire 32 H dbg_r5 [31:0] $end
$var wire 32 I dbg_r6 [31:0] $end
$var wire 32 J dmem_addr [31:0] $end
$var wire 1 < dmem_req $end
$var wire 32 K dmem_wdata [31:0] $end
$var wire 1 @ rst $end
$var wire 1 5 imem_req $end
$var wire 1 6 imem_ready $end
$var wire 32 L imem_rdata [31:0] $end
$var wire 32 M imem_addr [31:0] $end
$var wire 1 ; dmem_we $end
$var wire 1 = dmem_ready $end
$var wire 32 N dmem_rdata [31:0] $end
$var reg 32 O instr [31:0] $end
$var reg 32 P pc [31:0] $end
$var integer 32 Q i [31:0] $end
$upscope $end
$scope module dram $end
$var wire 1 ? clk $end
$var wire 1 R dbg_dram_busy $end
$var wire 1 @ rst $end
$var wire 1 & we $end
$var wire 128 S wdata [127:0] $end
$var wire 1 ( req $end
$var wire 32 T addr [31:0] $end
$var reg 4 U counter [3:0] $end
$var reg 128 V rdata [127:0] $end
$var reg 1 ) ready $end
$var reg 1 W waiting $end
$upscope $end
$scope module fwd $end
$var wire 5 X rd_mem [4:0] $end
$var wire 5 Y rd_wb [4:0] $end
$var wire 1 Z regwrite_mem $end
$var wire 1 [ regwrite_wb $end
$var wire 5 \ rs_ex [4:0] $end
$var wire 5 ] rt_ex [4:0] $end
$var reg 2 ^ forwardA [1:0] $end
$var reg 2 _ forwardB [1:0] $end
$upscope $end
$scope module hz $end
$var wire 1 ` memread_ex $end
$var wire 5 a rs_id [4:0] $end
$var wire 5 b rt_ex [4:0] $end
$var wire 5 c rt_id [4:0] $end
$var wire 1 % stall $end
$upscope $end
$scope module l1d $end
$var wire 1 ? clk $end
$var wire 32 d cpu_addr [31:0] $end
$var wire 1 < cpu_req $end
$var wire 32 e cpu_wdata [31:0] $end
$var wire 1 ; cpu_we $end
$var wire 1 f dbg_cache_miss $end
$var wire 32 g l2_addr [31:0] $end
$var wire 1 1 l2_req $end
$var wire 128 h l2_wdata [127:0] $end
$var wire 1 0 l2_we $end
$var wire 1 @ rst $end
$var wire 1 2 l2_ready $end
$var wire 128 i l2_rdata [127:0] $end
$var wire 1 j dbg_waiting $end
$var reg 32 k cpu_rdata [31:0] $end
$var reg 1 = cpu_ready $end
$var reg 1 l dirty_bit $end
$var reg 2 m state [1:0] $end
$upscope $end
$scope module l1i $end
$var wire 1 n cache_hit $end
$var wire 1 ? clk $end
$var wire 32 o cpu_addr [31:0] $end
$var wire 1 5 cpu_req $end
$var wire 1 p dbg_cache_miss $end
$var wire 32 q l2_addr [31:0] $end
$var wire 1 , l2_req $end
$var wire 1 @ rst $end
$var wire 1 - l2_ready $end
$var wire 128 r l2_rdata [127:0] $end
$var wire 1 s dbg_waiting $end
$var reg 32 t cpu_rdata [31:0] $end
$var reg 1 6 cpu_ready $end
$var reg 2 u state [1:0] $end
$upscope $end
$scope module l2 $end
$var wire 1 ? clk $end
$var wire 1 v dbg_l1d_active $end
$var wire 1 w dbg_l1i_active $end
$var wire 32 x l1d_addr [31:0] $end
$var wire 128 y l1d_rdata [127:0] $end
$var wire 1 2 l1d_ready $end
$var wire 1 1 l1d_req $end
$var wire 128 z l1d_wdata [127:0] $end
$var wire 1 0 l1d_we $end
$var wire 32 { l1i_addr [31:0] $end
$var wire 128 | l1i_rdata [127:0] $end
$var wire 1 - l1i_ready $end
$var wire 1 , l1i_req $end
$var wire 128 } mem_rdata [127:0] $end
$var wire 1 ) mem_ready $end
$var wire 1 ( mem_req $end
$var wire 128 ~ mem_wdata [127:0] $end
$var wire 1 & mem_we $end
$var wire 1 @ rst $end
$var wire 32 !" mem_addr [31:0] $end
$var reg 2 "" state [1:0] $end
$upscope $end
$upscope $end
$enddefinitions $end
$comment Show the parameter values. $end
$dumpall
$end
#0
$dumpvars
b0 ""
b0 !"
b0 ~
bx }
bx |
b0 {
b0 z
bx y
b0 x
0w
xv
b0 u
bx t
1s
bx r
b0 q
0p
b0 o
0n
b0 m
0l
bx k
1j
bx i
b0 h
b0 g
xf
b0 e
b0 d
bx c
b0 b
bx a
0`
b0 _
b0 ^
bx ]
bx \
1[
1Z
b10 Y
b11 X
0W
bx V
b0 U
b0 T
b0 S
0R
b100000 Q
b0 P
bx O
bx N
b0 M
bx L
b0 K
b0 J
b0 I
b0 H
b0 G
b0 F
b0 E
b0 D
xC
0B
0A
1@
0?
bx >
0=
x<
x;
b0 :
b0 9
b0 8
bx 7
06
05
b0 4
bx 3
02
x1
x0
b0 /
bx .
0-
0,
b0 +
bx *
0)
x(
b0 '
x&
0%
x$
b0 #
b0 "
b0 !
$end
#5000
1?
#10000
0?
#15000
1?
#20000
1$
1C
1p
1(
0?
1w
1,
15
0@
#25000
1R
1W
b1 ""
b1 u
1?
#30000
0?
#35000
b1 U
1?
#40000
0?
#45000
b10 U
1?
#50000
0?
#55000
b11 U
1?
#60000
0?
#65000
b100 U
1?
#70000
0?
#75000
xC
0p
0s
1B
16
xj
xA
x=
1n
1-
x2
0$
b100000000000010000000000000101 7
b100000000000010000000000000101 L
b100000000000010000000000000101 t
b100000000000010000000000000101 >
b100000000000010000000000000101 N
b100000000000010000000000000101 k
0R
0W
1)
b10101100000001010000000000010000100011000000010100000000000100000000000000100010000110000010000000100000000000010000000000000101 .
b10101100000001010000000000010000100011000000010100000000000100000000000000100010000110000010000000100000000000010000000000000101 r
b10101100000001010000000000010000100011000000010100000000000100000000000000100010000110000010000000100000000000010000000000000101 |
b10101100000001010000000000010000100011000000010100000000000100000000000000100010000110000010000000100000000000010000000000000101 3
b10101100000001010000000000010000100011000000010100000000000100000000000000100010000110000010000000100000000000010000000000000101 i
b10101100000001010000000000010000100011000000010100000000000100000000000000100010000110000010000000100000000000010000000000000101 y
b10101100000001010000000000010000100011000000010100000000000100000000000000100010000110000010000000100000000000010000000000000101 *
b10101100000001010000000000010000100011000000010100000000000100000000000000100010000110000010000000100000000000010000000000000101 V
b10101100000001010000000000010000100011000000010100000000000100000000000000100010000110000010000000100000000000010000000000000101 }
b101 U
1?
#80000
0?
#85000
1C
1p
1s
0B
06
0f
1j
0A
0=
0v
01
0<
0n
0-
02
1$
b100 +
b100 T
b100 !"
b1000100001100000100000 7
b1000100001100000100000 L
b1000100001100000100000 t
0&
00
0;
b0 a
b1 c
b0 \
b1 ]
b0 U
1R
1W
0)
b10 ""
b10 u
b100 /
b100 q
b100 {
b100 8
b100 M
b100 P
b100 o
b101 D
b100000000000010000000000000101 O
1?
#90000
0?
#95000
b1 u
b1 ""
b1 U
1?
#100000
0?
#105000
b10 U
1?
#110000
0?
#115000
b11 U
1?
#120000
0?
#125000
b100 U
1?
#130000
0?
#135000
0C
0p
0s
1B
16
1n
1-
0$
0R
0W
1)
b101 U
1?
#140000
0?
#145000
1C
1p
1s
0B
06
b1 9
b1 _
0n
0-
1$
b1000 +
b1000 T
b1000 !"
b10001100000001010000000000010000 7
b10001100000001010000000000010000 L
b10001100000001010000000000010000 t
b1 a
b10 c
b1 \
b10 ]
b0 U
1R
1W
0)
b10 ""
b10 u
b1000 /
b1000 q
b1000 {
b1000 8
b1000 M
b1000 P
b1000 o
b101 F
b1000100001100000100000 O
1?
#150000
0?
#155000
b1 u
b1 ""
b1 U
1?
#160000
0?
#165000
b10 U
1?
#170000
0?
#175000
b11 U
1?
#180000
0?
#185000
b100 U
1?
#190000
0?
#195000
0C
0p
0s
1B
16
1n
1-
0$
0R
0W
1)
b101 U
1?
#200000
0?
#205000
1C
1f
1p
1s
0B
06
1v
11
1<
b0 9
b0 _
0n
0-
1$
b0 +
b0 T
b0 !"
b10101100000001010000000000010000 7
b10101100000001010000000000010000 L
b10101100000001010000000000010000 t
b0 a
b101 c
b0 \
b101 ]
b0 U
1R
1W
0)
b10 ""
b10 u
b1100 /
b1100 q
b1100 {
b1100 8
b1100 M
b1100 P
b1100 o
b10001100000001010000000000010000 O
1?
#210000
0?
#215000
b1 u
b1 m
b1 ""
b1 U
1?
#220000
0?
#225000
b10 U
1?
#230000
0?
#235000
b11 U
1?
#240000
0?
#245000
b100 U
1?
#250000
0?
#255000
0C
0p
0s
1B
16
0f
0j
1A
1=
1n
1-
12
0$
0R
0W
1)
b101 U
1?
#260000
0?
#265000
1C
1p
1s
0B
06
1f
1j
0A
0=
0n
0-
02
1$
b100000000000010000000000000101 7
b100000000000010000000000000101 L
b100000000000010000000000000101 t
1&
10
1;
b0 U
1R
1W
0)
b10 ""
b10 m
b10 u
b10000 /
b10000 q
b10000 {
b10000 8
b10000 M
b10000 P
b10000 o
b10101100000001010000000000010000 O
1?
#270000
0?
#275000
b1 u
b1 m
1l
b1 ""
b1 U
1?
#280000
0?
#285000
b10 U
1?
#290000
0?
#295000
b11 U
1?
#300000
0?
#305000
b100 U
1?
#310000
0?
#315000
0C
0p
0s
1B
16
0f
0j
1A
1=
1n
1-
12
0$
0R
0W
1)
b101 U
1?
#320000
0?
#325000
1C
b10100 +
b10100 T
b10100 !"
1p
1s
0B
06
1j
0A
0=
0v
01
0<
0n
0-
02
1$
b1000100001100000100000 7
b1000100001100000100000 L
b1000100001100000100000 t
0&
00
0;
b1 c
b1 ]
b0 U
1R
1W
0)
b10 ""
b10 m
b10 u
b10100 /
b10100 q
b10100 {
b10100 8
b10100 M
b10100 P
b10100 o
b100000000000010000000000000101 O
1?
#330000
0?
#335000
b1 u
b1 ""
b1 U
1?
#340000
0?
#345000
b10 U
1?
#350000
0?
#355000
b11 U
1?
#360000
0?
#365000
b100 U
1?
#370000
0?
#375000
0C
0p
0s
1B
16
1n
1-
0$
b100000001000100000000000001010 7
b100000001000100000000000001010 L
b100000001000100000000000001010 t
b11001000011000000100000 >
b11001000011000000100000 N
b11001000011000000100000 k
0R
0W
1)
b1101000110010000000000111111110010000000100010000000000000101000000000011001000011000000100000 .
b1101000110010000000000111111110010000000100010000000000000101000000000011001000011000000100000 r
b1101000110010000000000111111110010000000100010000000000000101000000000011001000011000000100000 |
b1101000110010000000000111111110010000000100010000000000000101000000000011001000011000000100000 3
b1101000110010000000000111111110010000000100010000000000000101000000000011001000011000000100000 i
b1101000110010000000000111111110010000000100010000000000000101000000000011001000011000000100000 y
b1101000110010000000000111111110010000000100010000000000000101000000000011001000011000000100000 *
b1101000110010000000000111111110010000000100010000000000000101000000000011001000011000000100000 V
b1101000110010000000000111111110010000000100010000000000000101000000000011001000011000000100000 }
b101 U
1?
#380000
0?
#385000
1C
1p
1s
0B
06
b1 9
b1 _
0n
0-
1$
b11000 +
b11000 T
b11000 !"
b110100011001000000000011111111 7
b110100011001000000000011111111 L
b110100011001000000000011111111 t
b1 a
b10 c
b1 \
b10 ]
b0 U
1R
1W
0)
b10 ""
b10 u
b11000 /
b11000 q
b11000 {
b11000 8
b11000 M
b11000 P
b11000 o
b1111 E
b100000001000100000000000001010 O
1?
#390000
0?
#395000
b1 u
b1 ""
b1 U
1?
#400000
0?
#405000
b10 U
1?
#410000
0?
#415000
b11 U
1?
#420000
0?
#425000
b100 U
1?
#430000
0?
#435000
0C
0p
0s
1B
16
1n
1-
0$
0R
0W
1)
b101 U
1?
#440000
0?
#445000
1C
1p
1s
0B
06
b10 :
b10 ^
b0 9
b0 _
0n
0-
1$
b11100 +
b11100 T
b11100 !"
b0 7
b0 L
b0 t
b11 a
b100 c
b11 \
b100 ]
b0 U
1R
1W
0)
b10 ""
b10 u
b11100 /
b11100 q
b11100 {
b11100 8
b11100 M
b11100 P
b11100 o
b11111111 G
b110100011001000000000011111111 O
1?
#450000
0?
#455000
b1 u
b1 ""
b1 U
1?
#460000
0?
#465000
b10 U
1?
#470000
0?
#475000
b11 U
1?
#480000
0?
#485000
b100 U
1?
#490000
0?
#495000
0C
0p
0s
1B
16
1n
1-
0$
0R
0W
1)
b101 U
1?
#500000
0?
#505000
1C
1p
1s
0B
06
b0 :
b0 ^
0n
0-
1$
b100000 +
b100000 T
b100000 !"
b11001000011000000100000 7
b11001000011000000100000 L
b11001000011000000100000 t
b0 a
b0 c
b0 \
b0 ]
b0 U
1R
1W
0)
b10 ""
b10 u
b100000 /
b100000 q
b100000 {
b100000 8
b100000 M
b100000 P
b100000 o
b0 O
1?
#510000
0?
#515000
b1 u
b1 ""
b1 U
1?
#520000
0?
#525000
b10 U
1?
#530000
0?
#535000
b11 U
1?
#540000
0?
#545000
b100 U
1?
#550000
0?
#555000
0C
0p
0s
1B
16
1n
1-
0$
b10101100000010000000000000010100 7
b10101100000010000000000000010100 L
b10101100000010000000000000010100 t
b10101100000010000000000000010100 >
b10101100000010000000000000010100 N
b10101100000010000000000000010100 k
0R
0W
1)
b1000001100011100000000000000010000000011100001010000000010000010101100000010000000000000010100 .
b1000001100011100000000000000010000000011100001010000000010000010101100000010000000000000010100 r
b1000001100011100000000000000010000000011100001010000000010000010101100000010000000000000010100 |
b1000001100011100000000000000010000000011100001010000000010000010101100000010000000000000010100 3
b1000001100011100000000000000010000000011100001010000000010000010101100000010000000000000010100 i
b1000001100011100000000000000010000000011100001010000000010000010101100000010000000000000010100 y
b1000001100011100000000000000010000000011100001010000000010000010101100000010000000000000010100 *
b1000001100011100000000000000010000000011100001010000000010000010101100000010000000000000010100 V
b1000001100011100000000000000010000000011100001010000000010000010101100000010000000000000010100 }
b101 U
1?
#560000
0?
#565000
1C
1f
1p
1s
0B
06
1v
11
1<
0n
0-
1$
b0 +
b0 T
b0 !"
b111000010100000000100000 7
b111000010100000000100000 L
b111000010100000000100000 t
1&
10
1;
b1000 c
b1000 ]
b0 U
1R
1W
0)
b10 ""
b10 u
b100100 /
b100100 q
b100100 {
b100100 8
b100100 M
b100100 P
b100100 o
b10101100000010000000000000010100 O
1?
#570000
0?
#575000
b1 u
b1 m
b1 ""
b1 U
1?
#580000
0?
#585000
b10 U
1?
#590000
0?
#595000
b11 U
1?
#600000
0?
#605000
b100 U
1?
#610000
0?
#615000
0C
0p
0s
1B
16
0f
0j
1A
1=
1n
1-
12
0$
b1000100001100000100000 7
b1000100001100000100000 L
b1000100001100000100000 t
b100000000000010000000000000101 >
b100000000000010000000000000101 N
b100000000000010000000000000101 k
0R
0W
1)
b10101100000001010000000000010000100011000000010100000000000100000000000000100010000110000010000000100000000000010000000000000101 .
b10101100000001010000000000010000100011000000010100000000000100000000000000100010000110000010000000100000000000010000000000000101 r
b10101100000001010000000000010000100011000000010100000000000100000000000000100010000110000010000000100000000000010000000000000101 |
b10101100000001010000000000010000100011000000010100000000000100000000000000100010000110000010000000100000000000010000000000000101 3
b10101100000001010000000000010000100011000000010100000000000100000000000000100010000110000010000000100000000000010000000000000101 i
b10101100000001010000000000010000100011000000010100000000000100000000000000100010000110000010000000100000000000010000000000000101 y
b10101100000001010000000000010000100011000000010100000000000100000000000000100010000110000010000000100000000000010000000000000101 *
b10101100000001010000000000010000100011000000010100000000000100000000000000100010000110000010000000100000000000010000000000000101 V
b10101100000001010000000000010000100011000000010100000000000100000000000000100010000110000010000000100000000000010000000000000101 }
b101 U
1?
#620000
0?
#625000
1C
b101000 +
b101000 T
b101000 !"
1p
1s
0B
06
1j
0A
0=
0v
01
0<
b1 9
b1 _
0n
0-
02
1$
b10001100000001010000000000010000 7
b10001100000001010000000000010000 L
b10001100000001010000000000010000 t
0&
00
0;
b1 a
b10 c
b1 \
b10 ]
b0 U
1R
1W
0)
b10 ""
b10 m
b10 u
b101000 /
b101000 q
b101000 {
b101000 8
b101000 M
b101000 P
b101000 o
b10100 F
b1000100001100000100000 O
1?
#630000
0?
#635000
b1 u
b1 ""
b1 U
1?
#640000
0?
#645000
b10 U
1?
#650000
0?
#655000
b11 U
1?
#660000
0?
#665000
b100 U
1?
#670000
0?
