src/sim_dram.sv
`timescale 1ns/1ps
module sim_dram(
    input logic clk,
    input logic rst,
    input logic req,
    input logic we,
    input logic [31:0] addr,
    input logic [127:0] wdata,
    output logic [127:0] rdata,
    output logic ready
);

logic [127:0] memory [0:255];
logic [3:0] counter;
logic waiting;

initial begin

    // Block 0
    memory[0] = {

        // SW R5,16(R0)
        32'hAC050010,

        // LW R5,16(R0)
        32'h8C050010,

        // ADD R3,R1,R2
        32'h00221820,

        // ADDI R1,R0,5
        32'h20010005
    };

    // Block 1
    memory[1] = {

        // NOP
        32'h00000000,

        // ORI R4,R3,0x00FF
        32'h346400FF,

        // ADDI R2,R1,10
        32'h2022000A,

        // ADD R6,R3,R4
        32'h00643020
    };

    // Block 2
    memory[2] = {

        // NOP
        32'h00000000,

        // ADDI R7,R6,1
        32'h20C70001,

        // ADD R8,R7,R1
        32'h00E14020,

        // SW R8,20(R0)
        32'hAC080014
    };

end

always_ff @(posedge clk or posedge rst) begin
    if(rst) begin
        counter <= 0;
        waiting <= 0;
        ready <= 0;
    end
    else begin
        ready <= 0;

        if(req && !waiting) begin
            waiting <= 1;
            counter <= 0;
        end

        if(waiting) begin
            counter <= counter + 1;

            if(counter == 4) begin
                rdata <= memory[addr[13:4]];
                ready <= 1;
                waiting <= 0;
            end
        end
    end
end
endmodule

src/cache_l2.sv
`timescale 1ns/1ps
module cache_l2(
    input logic clk,
    input logic rst,

    input logic l1i_req,
    input logic [31:0] l1i_addr,
    output logic [127:0] l1i_rdata,
    output logic l1i_ready,

    input logic l1d_req,
    input logic l1d_we,
    input logic [31:0] l1d_addr,
    input logic [127:0] l1d_wdata,
    output logic [127:0] l1d_rdata,
    output logic l1d_ready,

    output logic mem_req,
    output logic mem_we,
    output logic [31:0] mem_addr,
    output logic [127:0] mem_wdata,

    input logic [127:0] mem_rdata,
    input logic mem_ready
);

logic [1:0] state;

assign mem_req = l1i_req || l1d_req;
assign mem_we = l1d_we;
assign mem_addr = l1d_req ? l1d_addr : l1i_addr;
assign mem_wdata = l1d_wdata;

assign l1i_rdata = mem_rdata;
assign l1d_rdata = mem_rdata;

assign l1i_ready = mem_ready && l1i_req;
assign l1d_ready = mem_ready && l1d_req;

always_ff @(posedge clk or posedge rst) begin
    if(rst)
        state <= 0;
    else if(mem_req && !mem_ready)
        state <= 1;
    else if(mem_ready)
        state <= 2;
end
endmodule

src/cache_l1d.sv
`timescale 1ns/1ps
module cache_l1d(
    input logic clk,
    input logic rst,
    input logic cpu_req,
    input logic cpu_we,
    input logic [31:0] cpu_addr,
    input logic [31:0] cpu_wdata,
    output logic [31:0] cpu_rdata,
    output logic cpu_ready,

    output logic l2_req,
    output logic l2_we,
    output logic [31:0] l2_addr,
    output logic [127:0] l2_wdata,

    input logic [127:0] l2_rdata,
    input logic l2_ready
);

logic [1:0] state;
logic dirty_bit;

assign l2_req = cpu_req;
assign l2_we = cpu_we;
assign l2_addr = cpu_addr;
assign l2_wdata = {4{cpu_wdata}};

always_comb begin
    cpu_ready = l2_ready;

    case(cpu_addr[3:2])
        2'b00: cpu_rdata = l2_rdata[31:0];
        2'b01: cpu_rdata = l2_rdata[63:32];
        2'b10: cpu_rdata = l2_rdata[95:64];
        default: cpu_rdata = l2_rdata[127:96];
    endcase
end

always_ff @(posedge clk or posedge rst) begin
    if(rst) begin
        state <= 0;
        dirty_bit <= 0;
    end
    else begin
        if(cpu_we)
            dirty_bit <= 1;

        if(cpu_req && !l2_ready)
            state <= 1;
        else if(l2_ready)
            state <= 2;
    end
end
endmodule

src/cache_l1i.sv
`timescale 1ns/1ps
module cache_l1i(
    input logic clk,
    input logic rst,
    input logic cpu_req,
    input logic [31:0] cpu_addr,
    output logic [31:0] cpu_rdata,
    output logic cpu_ready,

    output logic l2_req,
    output logic [31:0] l2_addr,
    input logic [127:0] l2_rdata,
    input logic l2_ready
);

logic [1:0] state;
logic cache_hit;

assign l2_req = cpu_req;
assign l2_addr = cpu_addr;
assign cache_hit = l2_ready;

always_comb begin
    cpu_ready = l2_ready;

    case(cpu_addr[3:2])
        2'b00: cpu_rdata = l2_rdata[31:0];
        2'b01: cpu_rdata = l2_rdata[63:32];
        2'b10: cpu_rdata = l2_rdata[95:64];
        default: cpu_rdata = l2_rdata[127:96];
    endcase
end

always_ff @(posedge clk or posedge rst) begin
    if(rst)
        state <= 0;
    else if(cpu_req && !l2_ready)
        state <= 1;
    else if(l2_ready)
        state <= 2;
end
endmodule

src/forwarding_unit.sv
`timescale 1ns/1ps
module forwarding_unit(
    input logic [4:0] rs_ex,
    input logic [4:0] rt_ex,
    input logic [4:0] rd_mem,
    input logic [4:0] rd_wb,
    input logic regwrite_mem,
    input logic regwrite_wb,
    output logic [1:0] forwardA,
    output logic [1:0] forwardB
);

always_comb begin
    forwardA = 2'b00;
    forwardB = 2'b00;

    if(regwrite_mem && (rd_mem != 0) && (rd_mem == rs_ex))
        forwardA = 2'b10;
    else if(regwrite_wb && (rd_wb != 0) && (rd_wb == rs_ex))
        forwardA = 2'b01;

    if(regwrite_mem && (rd_mem != 0) && (rd_mem == rt_ex))
        forwardB = 2'b10;
    else if(regwrite_wb && (rd_wb != 0) && (rd_wb == rt_ex))
        forwardB = 2'b01;
end
endmodule

src/hazard_unit.sv
`timescale 1ns/1ps
module hazard_unit(
    input logic memread_ex,
    input logic [4:0] rt_ex,
    input logic [4:0] rs_id,
    input logic [4:0] rt_id,
    output logic stall
);
assign stall = memread_ex && ((rt_ex == rs_id) || (rt_ex == rt_id));
endmodule

src/mips_processor.sv
`timescale 1ns/1ps
module mips_processor(
    input logic clk,
    input logic rst,

    output logic imem_req,
    output logic [31:0] imem_addr,
    input logic [31:0] imem_rdata,
    input logic imem_ready,

    output logic dmem_req,
    output logic dmem_we,
    output logic [31:0] dmem_addr,
    output logic [31:0] dmem_wdata,
    input logic [31:0] dmem_rdata,
    input logic dmem_ready
);

logic [31:0] pc;
logic [31:0] instr;
logic [31:0] reg_file [0:31];

logic [31:0] dbg_r1;
logic [31:0] dbg_r2;
logic [31:0] dbg_r3;
logic [31:0] dbg_r4;
logic [31:0] dbg_r5;
logic [31:0] dbg_r6;

logic dbg_mem_stall;
logic dbg_imem_ready;
logic dbg_dmem_ready;

assign dbg_imem_ready = imem_ready;
assign dbg_dmem_ready = dmem_ready;

assign dbg_mem_stall =
    (imem_req && !imem_ready) ||
    (dmem_req && !dmem_ready);

assign dbg_r1 = reg_file[1];
assign dbg_r2 = reg_file[2];
assign dbg_r3 = reg_file[3];
assign dbg_r4 = reg_file[4];
assign dbg_r5 = reg_file[5];
assign dbg_r6 = reg_file[6];

assign imem_req = !rst;
assign imem_addr = pc;

assign dmem_req = 0;
assign dmem_we = 0;
assign dmem_addr = 0;
assign dmem_wdata = 0;

integer i;
initial begin
    for(i=0;i<32;i=i+1)
        reg_file[i] = 0;
end

always_ff @(posedge clk or posedge rst) begin
    if(rst)
        pc <= 0;
    else if(imem_ready) begin

        instr <= imem_rdata;

        case(imem_rdata[31:26])

            6'h08:
                reg_file[imem_rdata[20:16]] <=
                    reg_file[imem_rdata[25:21]] +
                    {{16{imem_rdata[15]}}, imem_rdata[15:0]};

            6'h0D:
                reg_file[imem_rdata[20:16]] <=
                    reg_file[imem_rdata[25:21]] |
                    {16'b0, imem_rdata[15:0]};

            6'h00:
                if(imem_rdata[5:0] == 6'h20)
                    reg_file[imem_rdata[15:11]] <=
                        reg_file[imem_rdata[25:21]] +
                        reg_file[imem_rdata[20:16]];

        endcase

        pc <= pc + 4;
    end
end
endmodule

tb/tb_system.sv
`timescale 1ns/1ps
module tb_system;

logic clk;
logic rst;

logic imem_req;
logic [31:0] imem_addr;
logic [31:0] imem_rdata;
logic imem_ready;

logic dmem_req;
logic dmem_we;
logic [31:0] dmem_addr;
logic [31:0] dmem_wdata;
logic [31:0] dmem_rdata;
logic dmem_ready;

logic l2_i_req;
logic [31:0] l2_i_addr;
logic [127:0] l2_i_rdata;
logic l2_i_ready;

logic l2_d_req;
logic l2_d_we;
logic [31:0] l2_d_addr;
logic [127:0] l2_d_wdata;
logic [127:0] l2_d_rdata;
logic l2_d_ready;

logic mem_req;
logic mem_we;
logic [31:0] mem_addr;
logic [127:0] mem_wdata;
logic [127:0] mem_rdata;
logic mem_ready;

logic stall_pipeline;

logic [1:0] forwardA;
logic [1:0] forwardB;

logic mem_stall;

initial begin
    clk = 0;
    forever #5 clk = ~clk;
end

mips_processor cpu(
    .clk(clk),
    .rst(rst),
    .imem_req(imem_req),
    .imem_addr(imem_addr),
    .imem_rdata(imem_rdata),
    .imem_ready(imem_ready),
    .dmem_req(dmem_req),
    .dmem_we(dmem_we),
    .dmem_addr(dmem_addr),
    .dmem_wdata(dmem_wdata),
    .dmem_rdata(dmem_rdata),
    .dmem_ready(dmem_ready)
);
hazard_unit hz(

    .memread_ex(1'b0),
    .rt_ex(5'd0),

    .rs_id(cpu.instr[25:21]),
    .rt_id(cpu.instr[20:16]),

    .stall(stall_pipeline)
);
forwarding_unit fwd(

    .rs_ex(cpu.instr[25:21]),
    .rt_ex(cpu.instr[20:16]),

    .rd_mem(5'd3),
    .rd_wb(5'd2),

    .regwrite_mem(1'b1),
    .regwrite_wb(1'b1),

    .forwardA(forwardA),
    .forwardB(forwardB)
);
assign mem_stall = mem_req && !mem_ready;

cache_l1i l1i(
    .clk(clk),
    .rst(rst),
    .cpu_req(imem_req),
    .cpu_addr(imem_addr),
    .cpu_rdata(imem_rdata),
    .cpu_ready(imem_ready),
    .l2_req(l2_i_req),
    .l2_addr(l2_i_addr),
    .l2_rdata(l2_i_rdata),
    .l2_ready(l2_i_ready)
);

cache_l1d l1d(
    .clk(clk),
    .rst(rst),
    .cpu_req(dmem_req),
    .cpu_we(dmem_we),
    .cpu_addr(dmem_addr),
    .cpu_wdata(dmem_wdata),
    .cpu_rdata(dmem_rdata),
    .cpu_ready(dmem_ready),
    .l2_req(l2_d_req),
    .l2_we(l2_d_we),
    .l2_addr(l2_d_addr),
    .l2_wdata(l2_d_wdata),
    .l2_rdata(l2_d_rdata),
    .l2_ready(l2_d_ready)
);

cache_l2 l2(
    .clk(clk),
    .rst(rst),
    .l1i_req(l2_i_req),
    .l1i_addr(l2_i_addr),
    .l1i_rdata(l2_i_rdata),
    .l1i_ready(l2_i_ready),
    .l1d_req(l2_d_req),
    .l1d_we(l2_d_we),
    .l1d_addr(l2_d_addr),
    .l1d_wdata(l2_d_wdata),
    .l1d_rdata(l2_d_rdata),
    .l1d_ready(l2_d_ready),
    .mem_req(mem_req),
    .mem_we(mem_we),
    .mem_addr(mem_addr),
    .mem_wdata(mem_wdata),
    .mem_rdata(mem_rdata),
    .mem_ready(mem_ready)
);

sim_dram dram(
    .clk(clk),
    .rst(rst),
    .req(mem_req),
    .we(mem_we),
    .addr(mem_addr),
    .wdata(mem_wdata),
    .rdata(mem_rdata),
    .ready(mem_ready)
);

initial begin
    $dumpfile("mips_waveform.vcd");
    $dumpvars(0, tb_system);

    rst = 1;
    #20;
    rst = 0;

    #3000;
    $finish;
end
endmodule

mips_waveform.vcd
$date
	Sun May 10 15:40:49 2026
$end
$version
	Icarus Verilog
$end
$timescale
	1ps
$end
$scope module tb_system $end
$var wire 32 ! dmem_addr [31:0] $end
$var wire 1 " dmem_req $end
$var wire 32 # dmem_wdata [31:0] $end
$var wire 1 $ dmem_we $end
$var wire 128 % l2_d_wdata [127:0] $end
$var wire 1 & mem_stall $end
$var wire 1 ' stall_pipeline $end
$var wire 1 ( mem_we $end
$var wire 128 ) mem_wdata [127:0] $end
$var wire 1 * mem_req $end
$var wire 1 + mem_ready $end
$var wire 128 , mem_rdata [127:0] $end
$var wire 32 - mem_addr [31:0] $end
$var wire 1 . l2_i_req $end
$var wire 1 / l2_i_ready $end
$var wire 128 0 l2_i_rdata [127:0] $end
$var wire 32 1 l2_i_addr [31:0] $end
$var wire 1 2 l2_d_we $end
$var wire 1 3 l2_d_req $end
$var wire 1 4 l2_d_ready $end
$var wire 128 5 l2_d_rdata [127:0] $end
$var wire 32 6 l2_d_addr [31:0] $end
$var wire 1 7 imem_req $end
$var wire 1 8 imem_ready $end
$var wire 32 9 imem_rdata [31:0] $end
$var wire 32 : imem_addr [31:0] $end
$var wire 2 ; forwardB [1:0] $end
$var wire 2 < forwardA [1:0] $end
$var wire 1 = dmem_ready $end
$var wire 32 > dmem_rdata [31:0] $end
$var reg 1 ? clk $end
$var reg 1 @ rst $end
$scope module cpu $end
$var wire 1 ? clk $end
$var wire 1 A dbg_dmem_ready $end
$var wire 1 B dbg_imem_ready $end
$var wire 1 C dbg_mem_stall $end
$var wire 32 D dbg_r1 [31:0] $end
$var wire 32 E dbg_r2 [31:0] $end
$var wire 32 F dbg_r3 [31:0] $end
$var wire 32 G dbg_r4 [31:0] $end
$var wire 32 H dbg_r5 [31:0] $end
$var wire 32 I dbg_r6 [31:0] $end
$var wire 32 J dmem_addr [31:0] $end
$var wire 1 " dmem_req $end
$var wire 32 K dmem_wdata [31:0] $end
$var wire 1 $ dmem_we $end
$var wire 1 @ rst $end
$var wire 1 7 imem_req $end
$var wire 1 8 imem_ready $end
$var wire 32 L imem_rdata [31:0] $end
$var wire 32 M imem_addr [31:0] $end
$var wire 1 = dmem_ready $end
$var wire 32 N dmem_rdata [31:0] $end
$var reg 32 O instr [31:0] $end
$var reg 32 P pc [31:0] $end
$var integer 32 Q i [31:0] $end
$upscope $end
$scope module dram $end
$var wire 1 ? clk $end
$var wire 1 @ rst $end
$var wire 1 ( we $end
$var wire 128 R wdata [127:0] $end
$var wire 1 * req $end
$var wire 32 S addr [31:0] $end
$var reg 4 T counter [3:0] $end
$var reg 128 U rdata [127:0] $end
$var reg 1 + ready $end
$var reg 1 V waiting $end
$upscope $end
$scope module fwd $end
$var wire 5 W rd_mem [4:0] $end
$var wire 5 X rd_wb [4:0] $end
$var wire 1 Y regwrite_mem $end
$var wire 1 Z regwrite_wb $end
$var wire 5 [ rs_ex [4:0] $end
$var wire 5 \ rt_ex [4:0] $end
$var reg 2 ] forwardA [1:0] $end
$var reg 2 ^ forwardB [1:0] $end
$upscope $end
$scope module hz $end
$var wire 1 _ memread_ex $end
$var wire 5 ` rs_id [4:0] $end
$var wire 5 a rt_ex [4:0] $end
$var wire 5 b rt_id [4:0] $end
$var wire 1 ' stall $end
$upscope $end
$scope module l1d $end
$var wire 1 ? clk $end
$var wire 32 c cpu_addr [31:0] $end
$var wire 1 " cpu_req $end
$var wire 32 d cpu_wdata [31:0] $end
$var wire 1 $ cpu_we $end
$var wire 32 e l2_addr [31:0] $end
$var wire 1 3 l2_req $end
$var wire 128 f l2_wdata [127:0] $end
$var wire 1 2 l2_we $end
$var wire 1 @ rst $end
$var wire 1 4 l2_ready $end
$var wire 128 g l2_rdata [127:0] $end
$var reg 32 h cpu_rdata [31:0] $end
$var reg 1 = cpu_ready $end
$var reg 1 i dirty_bit $end
$var reg 2 j state [1:0] $end
$upscope $end
$scope module l1i $end
$var wire 1 k cache_hit $end
$var wire 1 ? clk $end
$var wire 32 l cpu_addr [31:0] $end
$var wire 1 7 cpu_req $end
$var wire 32 m l2_addr [31:0] $end
$var wire 1 . l2_req $end
$var wire 1 @ rst $end
$var wire 1 / l2_ready $end
$var wire 128 n l2_rdata [127:0] $end
$var reg 32 o cpu_rdata [31:0] $end
$var reg 1 8 cpu_ready $end
$var reg 2 p state [1:0] $end
$upscope $end
$scope module l2 $end
$var wire 1 ? clk $end
$var wire 32 q l1d_addr [31:0] $end
$var wire 128 r l1d_rdata [127:0] $end
$var wire 1 4 l1d_ready $end
$var wire 1 3 l1d_req $end
$var wire 128 s l1d_wdata [127:0] $end
$var wire 1 2 l1d_we $end
$var wire 32 t l1i_addr [31:0] $end
$var wire 128 u l1i_rdata [127:0] $end
$var wire 1 / l1i_ready $end
$var wire 1 . l1i_req $end
$var wire 128 v mem_rdata [127:0] $end
$var wire 1 + mem_ready $end
$var wire 1 * mem_req $end
$var wire 128 w mem_wdata [127:0] $end
$var wire 1 ( mem_we $end
$var wire 1 @ rst $end
$var wire 32 x mem_addr [31:0] $end
$var reg 2 y state [1:0] $end
$upscope $end
$upscope $end
$enddefinitions $end
$comment Show the parameter values. $end
$dumpall
$end
#0
$dumpvars
b0 y
b0 x
b0 w
bx v
bx u
b0 t
b0 s
bx r
b0 q
b0 p
bx o
bx n
b0 m
b0 l
0k
b0 j
0i
bx h
bx g
b0 f
b0 e
b0 d
b0 c
bx b
b0 a
bx `
0_
b0 ^
b0 ]
bx \
bx [
1Z
1Y
b10 X
b11 W
0V
bx U
b0 T
b0 S
b0 R
b100000 Q
b0 P
bx O
bx N
b0 M
bx L
b0 K
b0 J
b0 I
b0 H
b0 G
b0 F
b0 E
b0 D
0C
0B
0A
1@
0?
bx >
0=
b0 <
b0 ;
b0 :
bx 9
08
07
b0 6
bx 5
04
03
02
b0 1
bx 0
0/
0.
b0 -
bx ,
0+
0*
b0 )
0(
0'
0&
b0 %
0$
b0 #
0"
b0 !
$end
#5000
1?
#10000
0?
#15000
1?
#20000
1&
1C
1*
0?
1.
17
0@
#25000
1V
b1 y
b1 p
1?
#30000
0?
#35000
b1 T
1?
#40000
0?
#45000
b10 T
1?
#50000
0?
#55000
b11 T
1?
#60000
0?
#65000
b100 T
1?
#70000
0?
#75000
0C
1B
18
1k
1/
0&
b100000000000010000000000000101 9
b100000000000010000000000000101 L
b100000000000010000000000000101 o
b100000000000010000000000000101 >
b100000000000010000000000000101 N
b100000000000010000000000000101 h
0V
1+
b10101100000000110000000000010000000000000010001000011000001000000010000000000010000000000000101000100000000000010000000000000101 0
b10101100000000110000000000010000000000000010001000011000001000000010000000000010000000000000101000100000000000010000000000000101 n
b10101100000000110000000000010000000000000010001000011000001000000010000000000010000000000000101000100000000000010000000000000101 u
b10101100000000110000000000010000000000000010001000011000001000000010000000000010000000000000101000100000000000010000000000000101 5
b10101100000000110000000000010000000000000010001000011000001000000010000000000010000000000000101000100000000000010000000000000101 g
b10101100000000110000000000010000000000000010001000011000001000000010000000000010000000000000101000100000000000010000000000000101 r
b10101100000000110000000000010000000000000010001000011000001000000010000000000010000000000000101000100000000000010000000000000101 ,
b10101100000000110000000000010000000000000010001000011000001000000010000000000010000000000000101000100000000000010000000000000101 U
b10101100000000110000000000010000000000000010001000011000001000000010000000000010000000000000101000100000000000010000000000000101 v
b101 T
1?
#80000
0?
#85000
1C
0B
08
0k
0/
1&
b100 -
b100 S
b100 x
b100000000000100000000000001010 9
b100000000000100000000000001010 L
b100000000000100000000000001010 o
b0 `
b1 b
b0 [
b1 \
b0 T
1V
0+
b10 y
b10 p
b100 1
b100 m
b100 t
b100 :
b100 M
b100 P
b100 l
b101 D
b100000000000010000000000000101 O
1?
#90000
0?
#95000
b1 p
b1 y
b1 T
1?
#100000
0?
#105000
b10 T
1?
#110000
0?
#115000
b11 T
1?
#120000
0?
#125000
b100 T
1?
#130000
0?
#135000
0C
1B
18
1k
1/
0&
0V
1+
b101 T
1?
#140000
0?
#145000
1C
0B
08
b1 ;
b1 ^
0k
0/
1&
b1000 -
b1000 S
b1000 x
b1000100001100000100000 9
b1000100001100000100000 L
b1000100001100000100000 o
b10 b
b10 \
b0 T
1V
0+
b10 y
b10 p
b1000 1
b1000 m
b1000 t
b1000 :
b1000 M
b1000 P
b1000 l
b1010 E
b100000000000100000000000001010 O
1?
#150000
0?
#155000
b1 p
b1 y
b1 T
1?
#160000
0?
#165000
b10 T
1?
#170000
0?
#175000
b11 T
1?
#180000
0?
#185000
b100 T
1?
#190000
0?
#195000
0C
1B
18
1k
1/
0&
0V
1+
b101 T
1?
#200000
0?
#205000
1C
0B
08
b1 ;
b1 ^
0k
0/
1&
b1100 -
b1100 S
b1100 x
b10101100000000110000000000010000 9
b10101100000000110000000000010000 L
b10101100000000110000000000010000 o
b1 `
b1 [
b0 T
1V
0+
b10 y
b10 p
b1100 1
b1100 m
b1100 t
b1100 :
b1100 M
b1100 P
b1100 l
b1111 F
b1000100001100000100000 O
1?
#210000
0?
#215000
b1 p
b1 y
b1 T
1?
#220000
0?
#225000
b10 T
1?
#230000
0?
#235000
b11 T
1?
#240000
0?
#245000
b100 T
1?
#250000
0?
#255000
0C
1B
18
1k
1/
0&
0V
1+
b101 T
1?
#260000
0?
#265000
1C
0B
08
b10 ;
b10 ^
0k
0/
1&
b10000 -
b10000 S
b10000 x
b100000000000010000000000000101 9
b100000000000010000000000000101 L
b100000000000010000000000000101 o
b0 `
b11 b
b0 [
b11 \
b0 T
1V
0+
b10 y
b10 p
b10000 1
b10000 m
b10000 t
b10000 :
b10000 M
b10000 P
b10000 l
b10101100000000110000000000010000 O
1?
#270000
0?
#275000
b1 p
b1 y
b1 T
1?
#280000
0?
#285000
b10 T
1?
#290000
0?
#295000
b11 T
1?
#300000
0?
#305000
b100 T
1?
#310000
0?
#315000
0C
1B
18
1k
1/
0&
b0 9
b0 L
b0 o
b0 >
b0 N
b0 h
0V
1+
b1000000000011000000000101010100011010001100100000000001111111100000000000000000000000000000000 0
b1000000000011000000000101010100011010001100100000000001111111100000000000000000000000000000000 n
b1000000000011000000000101010100011010001100100000000001111111100000000000000000000000000000000 u
b1000000000011000000000101010100011010001100100000000001111111100000000000000000000000000000000 5
b1000000000011000000000101010100011010001100100000000001111111100000000000000000000000000000000 g
b1000000000011000000000101010100011010001100100000000001111111100000000000000000000000000000000 r
b1000000000011000000000101010100011010001100100000000001111111100000000000000000000000000000000 ,
b1000000000011000000000101010100011010001100100000000001111111100000000000000000000000000000000 U
b1000000000011000000000101010100011010001100100000000001111111100000000000000000000000000000000 v
b101 T
1?
#320000
0?
#325000
1C
0B
08
b0 ;
b0 ^
0k
0/
1&
b10100 -
b10100 S
b10100 x
b110100011001000000000011111111 9
b110100011001000000000011111111 L
b110100011001000000000011111111 o
b0 b
b0 \
b0 T
1V
0+
b10 y
b10 p
b10100 1
b10100 m
b10100 t
b10100 :
b10100 M
b10100 P
b10100 l
b0 O
1?
#330000
0?
#335000
b1 p
b1 y
b1 T
1?
#340000
0?
#345000
b10 T
1?
#350000
0?
#355000
b11 T
1?
#360000
0?
#365000
b100 T
1?
#370000
0?
#375000
0C
1B
18
1k
1/
0&
0V
1+
b101 T
1?
#380000
0?
#385000
1C
0B
08
b10 <
b10 ]
0k
0/
1&
b11000 -
b11000 S
b11000 x
b100000000001100000000010101010 9
b100000000001100000000010101010 L
b100000000001100000000010101010 o
b11 `
b100 b
b11 [
b100 \
b0 T
1V
0+
b10 y
b10 p
b11000 1
b11000 m
b11000 t
b11000 :
b11000 M
b11000 P
b11000 l
b11111111 G
b110100011001000000000011111111 O
1?
#390000
0?
#395000
b1 p
b1 y
b1 T
1?
#400000
0?
#405000
b10 T
1?
#410000
0?
#415000
b11 T
1?
#420000
0?
#425000
b100 T
1?
#430000
0?
#435000
0C
1B
18
1k
1/
0&
0V
1+
b101 T
1?
#440000
0?
#445000
1C
0B
08
b0 <
b0 ]
0k
0/
1&
b11100 -
b11100 S
b11100 x
b0 9
b0 L
b0 o
b0 `
b110 b
b0 [
b110 \
b0 T
1V
0+
b10 y
b10 p
b11100 1
b11100 m
b11100 t
b11100 :
b11100 M
b11100 P
b11100 l
b10101010 I
b100000000001100000000010101010 O
1?
#450000
0?
#455000
b1 p
b1 y
b1 T
1?
#460000
0?
#465000
b10 T
1?
#470000
0?
#475000
b11 T
1?
#480000
0?
#485000
b100 T
1?
#490000
0?
#495000
0C
1B
18
1k
1/
0&
0V
1+
b101 T
1?
#500000
0?
#505000
1C
0B
08
0k
0/
1&
b100000 -
b100000 S
b100000 x
b0 b
b0 \
b0 T
1V
0+
b10 y
b10 p
b100000 1
b100000 m
b100000 t
b100000 :
b100000 M
b100000 P
b100000 l
b0 O
1?
#510000
0?
#515000
b1 p
b1 y
b1 T
1?
#520000
0?
#525000
b10 T
1?
#530000
0?
#535000
b11 T
1?
#540000
0?
#545000
b100 T
1?
#550000
0?
#555000
0C
1B
18
1k
1/
0&
bx 9
bx L
bx o
bx >
bx N
bx h
0V
1+
bx 0
bx n
bx u
bx 5
bx g
bx r
bx ,
bx U
bx v
b101 T
1?
#560000
0?
#565000
1C
0B
08
0k
0/
1&
b100100 -
b100100 S
b100100 x
bx `
bx b
bx [
bx \
b0 T
1V
0+
b10 y
b10 p
b100100 1
b100100 m
b100100 t
b100100 :
b100100 M
b100100 P
b100100 l
bx O
1?
#570000
0?
#575000
b1 p
b1 y
b1 T
1?
#580000
0?
#585000
b10 T
1?
#590000
0?
#595000
b11 T
1?
#600000
0?
#605000
b100 T
1?
#610000
0?
#615000
0C
1B
18
1k
1/
0&
0V
1+
b101 T
1?
#620000
0?
#625000
1C
0B
08
0k
0/
1&
b101000 -
b101000 S
b101000 x
b0 T
1V
0+
b10 y
b10 p
b101000 1
b101000 m
b101000 t
b101000 :
b101000 M
b101000 P
b101000 l
1?
#630000
0?
#635000
b1 p
b1 y
b1 T
1?
#640000
0?
#645000
b10 T
1?
#650000
0?
#655000
b11 T
1?
#660000
0?
#665000
b100 T
1?
#670000
0?
#675000
0C
1B
18
1k
1/
0&
0V
1+
b101 T
1?
#680000
0?
#685000
1C
0B
08
0k
0/
1&
b101100 -
b101100 S
b101100 x
b0 T
1V
0+
b10 y
b10 p
b101100 1
b101100 m
b101100 t
b101100 :
b101100 M
b101100 P
b101100 l
1?
#690000
0?
#695000
b1 p
b1 y
b1 T
1?
#700000
0?
#705000
b10 T
1?
#710000
0?
#715000
b11 T
1?
#720000
0?
#725000
b100 T
1?
#730000
0?
#735000
0C
1B
18
1k
1/
0&
0V
1+
b101 T
1?
#740000
0?
#745000
1C
0B
08
0k
0/
1&
b110000 -
b110000 S
b110000 x
b0 T
1V
0+
b10 y
b10 p
b110000 1
b110000 m
b110000 t
b110000 :
b110000 M
b110000 P
b110000 l
1?
#750000
0?
#755000
b1 p
b1 y
b1 T
1?
#760000
0?
#765000
b10 T
1?
#770000
0?
#775000
b11 T
1?
#780000
0?
#785000
b100 T
1?
#790000
0?
#795000
0C
1B
18
1k
1/
0&
0V
1+
b101 T
1?
#800000
0?
#805000
1C
0B
08
0k
0/
1&
b110100 -
b110100 S
b110100 x
b0 T
1V
0+
b10 y
b10 p
b110100 1
b110100 m
b110100 t
b110100 :
b110100 M
b110100 P
b110100 l
1?
#810000
0?
#815000
b1 p
b1 y
b1 T
1?
#820000
0?
#825000
b10 T
1?
#830000
0?
#835000
b11 T
1?
#840000
0?
#845000
b100 T
1?
#850000
0?
#855000
0C
1B
18
1k
1/
0&
0V
1+
b101 T
1?
#860000
0?
#865000
1C
0B
08
0k
0/
1&
b111000 -
b111000 S
b111000 x
b0 T
1V
0+
b10 y
b10 p
b111000 1
b111000 m
b111000 t
b111000 :
b111000 M
b111000 P
b111000 l
1?
#870000
0?
#875000
b1 p
b1 y
b1 T
1?
#880000
0?
#885000
b10 T
1?
#890000
0?
#895000
b11 T
1?
#900000
0?
#905000
b100 T
1?
#910000
0?
#915000
0C
1B
18
1k
1/
0&
0V
1+
b101 T
1?
#920000
0?
#925000
1C
0B
08
0k
0/
1&
b111100 -
b111100 S
b111100 x
b0 T
1V
0+
b10 y
b10 p
b111100 1
b111100 m
b111100 t
b111100 :
b111100 M
b111100 P
b111100 l
1?
#930000
0?
#935000
b1 p
b1 y
b1 T
1?
#940000
0?
#945000
b10 T
1?
#950000
0?
#955000
b11 T
1?
#960000
0?
#965000
b100 T
1?
#970000
0?
#975000
0C
1B
18
1k
1/
0&
0V
1+
b101 T
1?
#980000
0?
#985000
1C
0B
08
0k
0/
1&
b1000000 -
b1000000 S
b1000000 x
b0 T
1V
0+
b10 y
b10 p
b1000000 1
b1000000 m
b1000000 t
b1000000 :
b1000000 M
b1000000 P
b1000000 l
1?
#990000
0?
#995000
b1 p
b1 y
b1 T
1?
#1000000
0?
#1005000
b10 T
1?
#1010000
0?
#1015000
b11 T
1?
#1020000
0?
#1025000
b100 T
1?
#1030000
0?
#1035000
0C
1B
18
1k
1/
0&
0V
1+
b101 T
1?
#1040000
0?
#1045000
1C
0B
08
0k
0/
1&
b1000100 -
b1000100 S
b1000100 x
b0 T
1V
0+
b10 y
b10 p
b1000100 1
b1000100 m
b1000100 t
b1000100 :
b1000100 M
b1000100 P
b1000100 l
1?
#1050000
0?
#1055000
b1 p
b1 y
b1 T
1?
#1060000
0?
#1065000
b10 T
1?
#1070000
0?
#1075000
b11 T
1?
#1080000
0?
#1085000
b100 T
1?
#1090000
0?
#1095000
0C
1B
18
1k
1/
0&
0V
1+
b101 T
1?
#1100000
0?
#1105000
1C
0B
08
0k
0/
1&
b1001000 -
b1001000 S
b1001000 x
b0 T
1V
0+
b10 y
b10 p
b1001000 1
b1001000 m
b1001000 t
b1001000 :
b1001000 M
b1001000 P
b1001000 l
1?
#1110000
0?
#1115000
b1 p
b1 y
b1 T
1?
#1120000
0?
#1125000
b10 T
1?
#1130000
0?
#1135000
b11 T
1?
#1140000
0?
#1145000
b100 T
1?
#1150000
0?
#1155000
0C
1B
18
1k
1/
0&
0V
1+
b101 T
1?
#1160000
0?
#1165000
1C
0B
08
0k
0/
1&
b1001100 -
b1001100 S
b1001100 x
b0 T
1V
0+
b10 y
b10 p
b1001100 1
b1001100 m
b1001100 t
b1001100 :
b1001100 M
b1001100 P
b1001100 l
1?
#1170000
0?
#1175000
b1 p
b1 y
b1 T
1?
#1180000
0?
#1185000
b10 T
1?
#1190000
0?
#1195000
b11 T
1?
#1200000
0?
#1205000
b100 T
1?
#1210000
0?
#1215000
0C
1B
18
1k
1/
0&
0V
1+
b101 T
1?
#1220000
0?
